python_prtg/__init__.py
python_prtg/writermodule.c
python_prtg/writermodule.h
python_prtg/writers.py
python_prtg-1.0.3.dist-info/LICENSE
python_prtg-1.0.3.dist-info/METADATA
python_prtg-1.0.3.dist-info/WHEEL
python_prtg-1.0.3.dist-info/top_level.txt
python_prtg-1.0.3.dist-info/RECORD
